sll385/__init__.py
sll385/LinkedList.py
sll385-0.1.1.dist-info/LICENSE
sll385-0.1.1.dist-info/WHEEL
sll385-0.1.1.dist-info/METADATA
sll385-0.1.1.dist-info/RECORD
