Metadata-Version: 2.1
Name: sll385
Version: 0.1.1
Summary: Turn regular python lists into singly linked lists
License: MIT
Author: Tanner Oates
Author-email: tanner.oates97@gmail.com
Requires-Python: >=3.9,<4.0
Classifier: License :: OSI Approved :: MIT License
Classifier: Operating System :: OS Independent
Classifier: Programming Language :: Python :: 3
Classifier: Programming Language :: Python :: 3.9
Classifier: Programming Language :: Python :: 3.10
Classifier: Programming Language :: Python :: 3.11
Classifier: Programming Language :: Python :: 3
Requires-Dist: pytest (>=7.2.0,<8.0.0)
